ChangeLog
INSTALL
LICENSE
README
TODO
setup.py
dasty/__init__.py
dasty.egg-info/PKG-INFO
dasty.egg-info/SOURCES.txt
dasty.egg-info/dependency_links.txt
dasty.egg-info/top_level.txt
dasty/core/Entity.py
dasty/core/MMM.py
dasty/core/Material.py
dasty/core/Primitive.py
dasty/core/Quaternion.py
dasty/core/Scene.py
dasty/core/ViewPlatform.py
dasty/core/__init__.py
dasty/material/Phong.py
dasty/material/__init__.py
doc/css.css
doc/css_002.css
doc/fetch.png
doc/fetch_002.png
doc/fetch_003.png
doc/fetch_004.png
doc/index.html
example/Simple.py
test/SceneTest.py
test/ViewPlatformTest.py
test/__init__.py
test/testall.py
