Metadata-Version: 1.0
Name: dasty
Version: 0.1
Summary: Dasty: data structure for multi-models and multi-resolutions 3D scenes
Home-page: http://www.irit.fr/NatSim
Author: Vortex team, IRIT
Author-email: hoelt@irit.fr
License: http://www.cecill.info/licences/Licence_CeCILL-C_V1-en.html
Platform: any
Classifier: Development Status :: 3 - Alpha
Classifier: Intended Audience :: Developers
Classifier: License :: Other/Proprietary License
Classifier: Programming Language :: Python
Classifier: Topic :: Multimedia :: Graphics :: 3D Modeling
Classifier: Topic :: Multimedia :: Graphics :: 3D Rendering
Classifier: Topic :: Software Development :: Libraries :: Python Modules
Classifier: Operating System :: OS Independent
